{
  "hash": "97e45290",
  "configHash": "e2e2aa12",
  "lockfileHash": "014d83bb",
  "browserHash": "532e15e7",
  "optimized": {
    "react/jsx-dev-runtime": {
      "src": "../../node_modules/react/jsx-dev-runtime.js",
      "file": "react_jsx-dev-runtime.js",
      "fileHash": "7dee224f",
      "needsInterop": true
    },
    "react": {
      "src": "../../node_modules/react/index.js",
      "file": "react.js",
      "fileHash": "bdbe7c74",
      "needsInterop": true
    },
    "react-dom/client": {
      "src": "../../node_modules/react-dom/client.js",
      "file": "react-dom_client.js",
      "fileHash": "726a01d6",
      "needsInterop": true
    },
    "react-router-dom": {
      "src": "../../node_modules/react-router-dom/dist/index.mjs",
      "file": "react-router-dom.js",
      "fileHash": "d2d11a63",
      "needsInterop": false
    },
    "lucide-react": {
      "src": "../../node_modules/lucide-react/dist/esm/lucide-react.js",
      "file": "lucide-react.js",
      "fileHash": "715b7de7",
      "needsInterop": false
    }
  },
  "chunks": {
    "chunk-Y7WO5LRC": {
      "file": "chunk-Y7WO5LRC.js"
    },
    "chunk-QXQUWXKN": {
      "file": "chunk-QXQUWXKN.js"
    }
  }
}